account/__init__.py
account/_account.cpython-38-x86_64-linux-gnu.so
account/test.py
hello_pybind11-1.2.3.dist-info/METADATA
hello_pybind11-1.2.3.dist-info/WHEEL
hello_pybind11-1.2.3.dist-info/top_level.txt
hello_pybind11-1.2.3.dist-info/RECORD
