Metadata-Version: 2.1
Name: hello-pybind11
Version: 1.2.3
Summary: a minimal example package (with pybind11)
Author: Pablo Hernandez-Cerdan
License: MIT
Requires-Python: >=3.7
